promptbin/__init__.py
promptbin/app.py
promptbin/cli.py
promptbin/core/__init__.py
promptbin/core/config.py
promptbin/core/container.py
promptbin/core/exceptions.py
promptbin/managers/__init__.py
promptbin/managers/prompt_manager.py
promptbin/managers/share_manager.py
promptbin/managers/tunnel_manager.py
promptbin/mcp/__init__.py
promptbin/mcp/server.py
promptbin/utils/__init__.py
promptbin/utils/build_check.py
promptbin/utils/flask_manager.py
promptbin/utils/install_devtunnel.py
promptbin/utils/setup_checker.py
promptbin/web/__init__.py
promptbin/web/static/css/style.css
promptbin/web/templates/404.html
promptbin/web/templates/500.html
promptbin/web/templates/base.html
promptbin/web/templates/create.html
promptbin/web/templates/edit.html
promptbin/web/templates/index.html
promptbin/web/templates/share.html
promptbin/web/templates/view.html
promptbin/web/templates/partials/create_content.html
promptbin/web/templates/partials/edit_content.html
promptbin/web/templates/partials/index_content.html
promptbin/web/templates/partials/navigation.html
promptbin/web/templates/partials/preview_pane.html
promptbin/web/templates/partials/prompt_card.html
promptbin/web/templates/partials/prompt_card_htmx.html
promptbin/web/templates/partials/search_results.html
promptbin/web/templates/partials/view_content.html
promptbin-0.5.1.dist-info/METADATA
promptbin-0.5.1.dist-info/WHEEL
promptbin-0.5.1.dist-info/entry_points.txt
promptbin-0.5.1.dist-info/licenses/LICENSE
promptbin-0.5.1.dist-info/RECORD
