Metadata-Version: 2.4
Name: promptbin
Version: 0.5.1
Summary: Easy-to-use MCP server for prompt management with web interface and secure sharing
Project-URL: Homepage, https://github.com/ianphil/promptbin
Project-URL: Repository, https://github.com/ianphil/promptbin
Project-URL: Issues, https://github.com/ianphil/promptbin/issues
Project-URL: Documentation, https://github.com/ianphil/promptbin#readme
Author-email: PromptBin Contributors <noreply@promptbin.dev>
Maintainer-email: PromptBin Contributors <noreply@promptbin.dev>
License-File: LICENSE
Keywords: ai,chatgpt,claude,mcp,model-context-protocol,prompt-management,prompts
Classifier: Development Status :: 4 - Beta
Classifier: Environment :: Web Environment
Classifier: Framework :: Flask
Classifier: Intended Audience :: Developers
Classifier: License :: OSI Approved :: MIT License
Classifier: Operating System :: OS Independent
Classifier: Programming Language :: Python :: 3
Classifier: Programming Language :: Python :: 3.11
Classifier: Programming Language :: Python :: 3.12
Classifier: Topic :: Internet :: WWW/HTTP :: WSGI :: Application
Classifier: Topic :: Scientific/Engineering :: Artificial Intelligence
Classifier: Topic :: Software Development :: Libraries :: Python Modules
Requires-Python: >=3.11
Requires-Dist: flask<4.0.0,>=3.0.0
Requires-Dist: markdown<4.0.0,>=3.5.0
Requires-Dist: mcp[cli]<2.0.0,>=1.0.0
Requires-Dist: psutil<6.0.0,>=5.9.0
Requires-Dist: python-dotenv<2.0.0,>=1.0.0
Requires-Dist: requests<3.0.0,>=2.31.0
